MANIFEST.in
README.md
setup.py
SQLShare_client.egg-info/PKG-INFO
SQLShare_client.egg-info/SOURCES.txt
SQLShare_client.egg-info/dependency_links.txt
SQLShare_client.egg-info/requires.txt
SQLShare_client.egg-info/top_level.txt
sqlshare_client/VERSION
sqlshare_client/__init__.py
sqlshare_client/base.py
sqlshare_client/client.py
sqlshare_client/datasets.py
sqlshare_client/exceptions.py
sqlshare_client/oauth.py
sqlshare_client/query.py
sqlshare_client/users.py
sqlshare_client/scripts/sqlshare_all_datasets
sqlshare_client/scripts/sqlshare_create_from_sql
sqlshare_client/scripts/sqlshare_list_queries
sqlshare_client/scripts/sqlshare_my_datasets
sqlshare_client/scripts/sqlshare_permissions
sqlshare_client/scripts/sqlshare_run_query
sqlshare_client/scripts/sqlshare_shared_datasets
sqlshare_client/scripts/sqlshare_show_dataset
sqlshare_client/scripts/sqlshare_upload_file
sqlshare_client/scripts/sqlshare_whoami
sqlshare_client/util/__init__.py
sqlshare_client/util/command_line.py
sqlshare_client/util/scripts.py