Metadata-Version: 1.1
Name: SQLShare-client
Version: 0.5.1a3
Summary: A library for accessing SQLShare REST Services
Home-page: https://github.com/uw-it-aca/sqlshare-client/wiki/Client-documentation
Author: UW-IT AXDD
Author-email: aca-it@uw.edu
License: Apache License, Version 2.0
Platform: UNKNOWN
Classifier: Intended Audience :: Developers
Classifier: License :: OSI Approved :: Apache Software License
Classifier: Operating System :: OS Independent
Classifier: Programming Language :: Python
Classifier: Programming Language :: Python :: 2.7
Classifier: Programming Language :: Python :: 3.4
